jl95/pytools/README.md
jl95/pytools/env.py
jl95/pytools/envlib/__init__.py
jl95/pytools/envlib/state.py
jl95/pytools/envlib/vars/__init__.py
jl95/pytools/envlib/vars/builtin.py
jl95terceira/pytools/README.md
jl95terceira/pytools/env.py
jl95terceira/pytools/envlib/__init__.py
jl95terceira/pytools/envlib/state.py
jl95terceira/pytools/envlib/vars/__init__.py
jl95terceira/pytools/envlib/vars/builtin.py
jl95terceira_pytools_env-0.2.8.dist-info/METADATA
jl95terceira_pytools_env-0.2.8.dist-info/WHEEL
jl95terceira_pytools_env-0.2.8.dist-info/entry_points.txt
jl95terceira_pytools_env-0.2.8.dist-info/RECORD
