Metadata-Version: 2.4
Name: jl95terceira_pytools_env
Version: 0.2.8
Summary: Environment / State support, intended for use by CLI tools
Project-URL: Homepage, https://github.com/jl95terceira/project-env
Project-URL: Issues, https://github.com/jl95terceira/project-env/issues
Author-email: Joao Luis Ornelas da Silva <jl95terceira@gmail.com>
Classifier: License :: OSI Approved :: MIT License
Classifier: Operating System :: OS Independent
Classifier: Programming Language :: Python :: 3
Requires-Python: >=3.12
Requires-Dist: jl95terceira-batteries>=1.3.1
